{
  "tasks": [
    {
      "id": 1,
      "text": "Doctor appointment",
      "day": "March 1st at 2:30pm",
      "reminder": false
    },
    {
      "id": 2,
      "text": "Meeting at school",
      "day": "March 21st at 9:30am",
      "reminder": false
    },
    {
      "id": 3,
      "text": "Shopping",
      "day": "March 2nd at 12:30pm",
      "reminder": true
    },
    {
      "id": 4,
      "text": "Deliver content",
      "day": "March 13th at 10:30am",
      "reminder": true
    },
    {
      "id": 5,
      "text": "Buy tickets",
      "day": "March 10th at 10:30pm",
      "reminder": false
    },
    {
      "id": 5876,
      "text": "Meet Sera",
      "day": "march 12 at 3 pm",
      "remidner": true
    }
  ]
}